rjango/__init__.py
rjango/pg/__init__.py
rjango.pg-0.1.0.dist-info/METADATA
rjango.pg-0.1.0.dist-info/WHEEL
rjango.pg-0.1.0.dist-info/top_level.txt
rjango.pg-0.1.0.dist-info/RECORD
